dlg_example_cmpts/__init__.py
dlg_example_cmpts/apps.py
dlg_example_cmpts/data.py
dlg_example_funcs/__init__.py
dlg_example_funcs/fourier_transform_algorithm.py
dlg_example_funcs/simple.py
dlg_example_cmpts-0.2.0.dist-info/LICENSE
dlg_example_cmpts-0.2.0.dist-info/METADATA
dlg_example_cmpts-0.2.0.dist-info/WHEEL
dlg_example_cmpts-0.2.0.dist-info/top_level.txt
dlg_example_cmpts-0.2.0.dist-info/RECORD
