Metadata-Version: 2.1
Name: dlg_example_cmpts
Version: 0.2.0
Summary: DALiuGE Component Examples created by ICRAR
Home-page: https://github.com/ICRAR/daliuge-component-examples/
Author: andreas.wicenec@icrar.org
License-File: LICENSE
Requires-Dist: daliuge-engine >=2.3.2
Requires-Dist: matplotlib
Requires-Dist: blockdag
Provides-Extra: test
Requires-Dist: pytest ; extra == 'test'
Requires-Dist: coverage ; extra == 'test'
Requires-Dist: flake8 ; extra == 'test'
Requires-Dist: black ; extra == 'test'
Requires-Dist: isort ; extra == 'test'
Requires-Dist: pytest-cov ; extra == 'test'
Requires-Dist: codecov ; extra == 'test'
Requires-Dist: mypy ; extra == 'test'
Requires-Dist: gitchangelog ; extra == 'test'
Requires-Dist: mkdocs ; extra == 'test'
